Workbook

Sheet News Articles 26
A1: article_id | B1: article_url | C1: article_title | D1: image_id
A2: 8501 | B2: https://resolver.kb.nl/resolve?urn=MMSAA06:165575032:mpeg21:p00001 | C2: The unveiling of the Iltis Monument in Shanghai. | D2: ff4fe3b12ab041cafc9b5655f3ec949e
A3: 8502 | B3: https://resolver.kb.nl/resolve?urn=MMSAA06:165575004:mpeg21:p00001 | C3: The demise of 'Burgundy'. | D3: 3d446f6d460b6c80ed8bb7eed7a608f3
A4: 8503 | B4: https://resolver.kb.nl/resolve?urn=MMSAA06:165575043:mpeg21:p00001 | C4: HH's visit MM. the queens at the Onze Lieve Vrouwe guesthouse. | D4: ecebad66d2b4fd4e7bbb2b97d57bb100
A5: 8504 | B5: https://resolver.kb.nl/resolve?urn=MMRHCE02:163620058:mpeg21:p00001 | C5: BENIGN DISEASE EISENHOWER'S CONDITION VERY SATISFACTORY | D5: 5bf04fd98212fe2e25fce8125247cc10
A6: 8505 | B6: https://resolver.kb.nl/resolve?urn=MMRHCE02:163620040:mpeg21:p00001 | C6: Three Thunderstreaks crashed over Gelderland. PILOTS ABLE TO SAVE THEMSELVES WITH EJECTION SEAT Lack of fuel | D6: 92c89d592e630ab686e72a8c3b96226e
A7: 8506 | B7: https://resolver.kb.nl/resolve?urn=MMRHCE02:163636034:mpeg21:p00001 | C7: Moscow against 'free airspace' KROESJEF DOES NOT CHANGE JUDGMENT ABOUT IKE US PRESIDENT TO RUSSIA? MOSCOW-WASHINGTON, May 12. | D7: fe269637ca212eaba179461c6e6570fa
A8: 8507 | B8: https://resolver.kb.nl/resolve?urn=MMRHCE02:163635070:mpeg21:p00001 | C8: Situation in South Africa still tense DEATH TOTAL RISE TO 66 JOHANNESBURG Cape Town, March 23 (Reuter A.P.). | D8: 93ad24f5fd48351a74dfe1ac691fdf20
A9: 8508 | B9: https://resolver.kb.nl/resolve?urn=ABCDDD:010814016:mpeg21:p001 | C9: Heavy fighting during Israeli punitive expedition in Jordan TWELVE HOURS OF WAR IN MIDDLE EAST TEL AVIV/AMMAN | D9: 084d9c4182d5568b0d8903e874894cf0
A10: 8509 | B10: https://resolver.kb.nl/resolve?urn=ABCDDD:010814041:mpeg21:p001 | C10: Johnson accepts surprising offer from government in Hanoi US AND ND-VIETNAM TO TALK HANOI, SAIGON, WASHINGTON (AP, UPI, Reuter) - President Johnson wants to make contact with representatives of North Vietnam, now that Hanoi is willing to talk. | D10: 97d549c5e67ccf8305999b2ff14387d5
A11: 8510 | B11: https://resolver.kb.nl/resolve?urn=ABCDDD:010814047:mpeg21:p001 | C11: SAIGON STRENGTHENS ARMY 'to prepare peace' | D11: c032a4cdc9beb794e1716b5e8303136d
A12: 8511 | B12: https://resolver.kb.nl/resolve?urn=ABCDDD:010880247:mpeg21:p001 | C12: Landslide French elections De Gaulle's great triumph: absolute majority | D12: dd01a756e57d52f9a86b53fed235c7fb
A13: 8512 | B13: https://resolver.kb.nl/resolve?urn=ABCDDD:010880263:mpeg21:p001 | C13: LETTER FROM WARSAW REJECTED Doebsek: we will continue | D13: b7bc7d667610be21b9799fe39ee86995
... A15181: 23680 | B15181: https://assets.msn.com/labs/mind/BBWzQEU.html | C15181: CNN reporter: This is the tense calm after protester shot | D15181: cff84d1b64094d84867ee5bcb64a7a87

Sheet Test
A1: article_id | B1: article_url | C1: article_title | D1: image_id
A2: 8501 | B2: N/A | C2: =VLOOKUP(A2,'News Articles 26'!$A$2:$D$15181,3) -> The unveiling of the Iltis Monument in Shanghai. | D2: N/A
A3: 8504 | B3: N/A | C3: =VLOOKUP(A3,'News Articles 26'!$A$2:$D$15181,3) -> BENIGN DISEASE EISENHOWER'S CONDITION VERY SATISFACTORY | D3: N/A
A4: 8509 | B4: N/A | C4: =VLOOKUP(A4,'News Articles 26'!$A$2:$D$15181,3) -> Johnson accepts surprising offer from government in Hanoi US AND ND-VIETNAM TO TALK HANOI, SAIGON, WASHINGTON (AP, UPI, Reuter) - President Johnson wants to make contact with representatives of North Vietnam, now that Hanoi is willing to talk. | D4: N/A
A5: 8511 | B5: N/A | C5: =VLOOKUP(A5,'News Articles 26'!$A$2:$D$15181,3) -> Landslide French elections De Gaulle's great triumph: absolute majority | D5: N/A
A6: 8516 | B6: N/A | C6: =VLOOKUP(A6,'News Articles 26'!$A$2:$D$15181,3) -> British-Dutch cooperation MARINE DEPLOYED ON OIL ROUTE Frigate patrol to Indian Ocean | D6: N/A
A7: 8517 | B7: N/A | C7: =VLOOKUP(A7,'News Articles 26'!$A$2:$D$15181,3) -> Chile turns to Russia Allende in Moscow for more help | D7: N/A
A8: 8519 | B8: N/A | C8: =VLOOKUP(A8,'News Articles 26'!$A$2:$D$15181,3) -> MORE THAN MILLION SPECTATORS Departure of Apollo 16 went smoothly | D8: N/A
A9: 8525 | B9: N/A | C9: =VLOOKUP(A9,'News Articles 26'!$A$2:$D$15181,3) -> RESISTANCE AGAINST KING GROWS Demonstrations for amnesty in Spain dispersed | D9: N/A
A10: 8526 | B10: N/A | C10: =VLOOKUP(A10,'News Articles 26'!$A$2:$D$15181,3) -> Fifty thousand demonstrators in Lisbon | D10: N/A
A11: 8527 | B11: N/A | C11: =VLOOKUP(A11,'News Articles 26'!$A$2:$D$15181,3) -> ECONOMIC PROBLEMS ARISING London is operating cautiously on the eve of the referendum. Unions are coming to their senses | D11: N/A
A12: 8528 | B12: N/A | C12: =VLOOKUP(A12,'News Articles 26'!$A$2:$D$15181,3) -> China concerned about the security of Western Europe | D12: N/A
A13: 8539 | B13: N/A | C13: =VLOOKUP(A13,'News Articles 26'!$A$2:$D$15181,3) -> China prepares Jimmy Carter a warm welcome | D13: N/A
... A801: 23663 | B801: N/A | C801: =VLOOKUP(A801,'News Articles 26'!$A$2:$D$15181,3) -> Portion of Parker Avenue under boil water advisory | D801: N/A

Sheet Evaluation
A1: article_id | B1: article_url | C1: article_title | D1: image_id
A2: ='News Articles 26'!A4 -> 8503 | B2: =IF(_xlfn.XLOOKUP(A2,Test!$A$2:$A$801,Test!$A$2:$A$801,0),"N/A",'News Articles 26'!B4) -> https://resolver.kb.nl/resolve?urn=MMSAA06:165575043:mpeg21:p00001 | C2: ='News Articles 26'!C4 -> HH's visit MM. the queens at the Onze Lieve Vrouwe guesthouse. | D2: =IF(B2="N/A","N/A",'News Articles 26'!D4) -> ecebad66d2b4fd4e7bbb2b97d57bb100
A3: ='News Articles 26'!A3 -> 8502 | B3: =IF(_xlfn.XLOOKUP(A3,Test!$A$2:$A$801,Test!$A$2:$A$801,0),"N/A",'News Articles 26'!B3) -> https://resolver.kb.nl/resolve?urn=MMSAA06:165575004:mpeg21:p00001 | C3: ='News Articles 26'!C3 -> The demise of 'Burgundy'. | D3: =IF(B3="N/A","N/A",'News Articles 26'!D3) -> 3d446f6d460b6c80ed8bb7eed7a608f3
A4: ='News Articles 26'!A7 -> 8506 | B4: =IF(_xlfn.XLOOKUP(A4,Test!$A$2:$A$801,Test!$A$2:$A$801,0),"N/A",'News Articles 26'!B7) -> https://resolver.kb.nl/resolve?urn=MMRHCE02:163636034:mpeg21:p00001 | C4: ='News Articles 26'!C7 -> Moscow against 'free airspace' KROESJEF DOES NOT CHANGE JUDGMENT ABOUT IKE US PRESIDENT TO RUSSIA? MOSCOW-WASHINGTON, May 12. | D4: =IF(B4="N/A","N/A",'News Articles 26'!D7) -> fe269637ca212eaba179461c6e6570fa
A5: ='News Articles 26'!A8 -> 8507 | B5: =IF(_xlfn.XLOOKUP(A5,Test!$A$2:$A$801,Test!$A$2:$A$801,0),"N/A",'News Articles 26'!B8) -> https://resolver.kb.nl/resolve?urn=MMRHCE02:163635070:mpeg21:p00001 | C5: ='News Articles 26'!C8 -> Situation in South Africa still tense DEATH TOTAL RISE TO 66 JOHANNESBURG Cape Town, March 23 (Reuter A.P.). | D5: =IF(B5="N/A","N/A",'News Articles 26'!D8) -> 93ad24f5fd48351a74dfe1ac691fdf20
A6: ='News Articles 26'!A6 -> 8505 | B6: =IF(_xlfn.XLOOKUP(A6,Test!$A$2:$A$801,Test!$A$2:$A$801,0),"N/A",'News Articles 26'!B6) -> https://resolver.kb.nl/resolve?urn=MMRHCE02:163620040:mpeg21:p00001 | C6: ='News Articles 26'!C6 -> Three Thunderstreaks crashed over Gelderland. PILOTS ABLE TO SAVE THEMSELVES WITH EJECTION SEAT Lack of fuel | D6: =IF(B6="N/A","N/A",'News Articles 26'!D6) -> 92c89d592e630ab686e72a8c3b96226e
A7: ='News Articles 26'!A34 -> 8533 | B7: =IF(_xlfn.XLOOKUP(A7,Test!$A$2:$A$801,Test!$A$2:$A$801,0),"N/A",'News Articles 26'!B34) -> https://resolver.kb.nl/resolve?urn=MMKB32:164680009:mpeg21:p00009 | C7: ='News Articles 26'!C34 -> THE VICTORIA THEATRE. | D7: =IF(B7="N/A","N/A",'News Articles 26'!D34) -> 9a0b6220034a069601e6fe5cc6cd5ad4
A8: ='News Articles 26'!A62 -> 8561 | B8: =IF(_xlfn.XLOOKUP(A8,Test!$A$2:$A$801,Test!$A$2:$A$801,0),"N/A",'News Articles 26'!B62) -> https://resolver.kb.nl/resolve?urn=MMKB19:000847039:mpeg21:p00001 | C8: ='News Articles 26'!C62 -> NATO conference opened by Pres. Eisenhower | D8: =IF(B8="N/A","N/A",'News Articles 26'!D62) -> 6adb248f59cfbb6e9756d48ae33f0bb4
A9: ='News Articles 26'!A87 -> 8586 | B9: =IF(_xlfn.XLOOKUP(A9,Test!$A$2:$A$801,Test!$A$2:$A$801,0),"N/A",'News Articles 26'!B87) -> https://resolver.kb.nl/resolve?urn=KBPERS01:003231022:mpeg21:p00018 | C9: ='News Articles 26'!C87 -> Dakar is not for fun. Westenberg and Van Eijk ride at full speed and finish | D9: =IF(B9="N/A","N/A",'News Articles 26'!D87) -> 97baa6ca582ba170e463291d77f0b431
A10: ='News Articles 26'!A86 -> 8585 | B10: =IF(_xlfn.XLOOKUP(A10,Test!$A$2:$A$801,Test!$A$2:$A$801,0),"N/A",'News Articles 26'!B86) -> https://resolver.kb.nl/resolve?urn=KBPERS01:003231022:mpeg21:p00011 | C10: ='News Articles 26'!C86 -> Waste is big business | D10: =IF(B10="N/A","N/A",'News Articles 26'!D86) -> d54bef148ed70d422503f1cd998b3a21
A11: ='News Articles 26'!A85 -> 8584 | B11: =IF(_xlfn.XLOOKUP(A11,Test!$A$2:$A$801,Test!$A$2:$A$801,0),"N/A",'News Articles 26'!B85) -> https://resolver.kb.nl/resolve?urn=KBPERS01:003231022:mpeg21:p00003 | C11: ='News Articles 26'!C85 -> Homeless people are 'talked into shelters' | D11: =IF(B11="N/A","N/A",'News Articles 26'!D85) -> 79fddac3e1b2bba8851848af46d9b004
A12: ='News Articles 26'!A83 -> 8582 | B12: =IF(_xlfn.XLOOKUP(A12,Test!$A$2:$A$801,Test!$A$2:$A$801,0),"N/A",'News Articles 26'!B83) -> https://resolver.kb.nl/resolve?urn=KBPERS01:003231013:mpeg21:p00007 | C12: ='News Articles 26'!C83 -> Putin visits Castro | D12: =IF(B12="N/A","N/A",'News Articles 26'!D83) -> 7b04b0a005c3ba3002e70adad799f4ac
A13: ='News Articles 26'!A82 -> 8581 | B13: =IF(_xlfn.XLOOKUP(A13,Test!$A$2:$A$801,Test!$A$2:$A$801,0),"N/A",'News Articles 26'!B82) -> https://resolver.kb.nl/resolve?urn=KBPERS01:003231013:mpeg21:p00006 | C13: ='News Articles 26'!C82 -> Fuel removed from Dodewaard without any problems | D13: =IF(B13="N/A","N/A",'News Articles 26'!D82) -> 19f920371fbc69882990d7629c35716d
A14: ='News Articles 26'!A81 -> 8580 | B14: =IF(_xlfn.XLOOKUP(A14,Test!$A$2:$A$801,Test!$A$2:$A$801,0),"N/A",'News Articles 26'!B81) -> https://resolver.kb.nl/resolve?urn=KBPERS01:003231013:mpeg21:p00003 | C14: ='News Articles 26'!C81 -> At least 100,000 hemp growers in the Netherlands | D14: =IF(B14="N/A","N/A",'News Articles 26'!D81) -> 7a8950a90728fa1707637eb3719497ef
A15: ='News Articles 26'!A79 -> 8578 | B15: =IF(_xlfn.XLOOKUP(A15,Test!$A$2:$A$801,Test!$A$2:$A$801,0),"N/A",'News Articles 26'!B79) -> https://resolver.kb.nl/resolve?urn=KBPERS01:003171014:mpeg21:p00013 | C15: ='News Articles 26'!C79 -> Still, fanfares at the commemoration of Marshall aid | D15: =IF(B15="N/A","N/A",'News Articles 26'!D79) -> 135586bebc9894cc13edfbedb590d29c
A16: ='News Articles 26'!A44 -> 8543 | B16: =IF(_xlfn.XLOOKUP(A16,Test!$A$2:$A$801,Test!$A$2:$A$801,0),"N/A",'News Articles 26'!B44) -> https://resolver.kb.nl/resolve?urn=KBPERS01:003165020:mpeg21:p00007 | C16: ='News Articles 26'!C44 -> Yeltsin dismisses government | D16: =IF(B16="N/A","N/A",'News Articles 26'!D44) -> bc2cb28e624cce38778cf8f04d3964df
A17: ='News Articles 26'!A58 -> 8557 | B17: =IF(_xlfn.XLOOKUP(A17,Test!$A$2:$A$801,Test!$A$2:$A$801,0),"N/A",'News Articles 26'!B58) -> https://resolver.kb.nl/resolve?urn=KBPERS01:003165009:mpeg21:p00008 | C17: ='News Articles 26'!C58 -> Many Chileans are not happy with Senator Pinochet | D17: =IF(B17="N/A","N/A",'News Articles 26'!D58) -> 423412ffdd72bdea2c77d9501fcdfdb6
A18: ='News Articles 26'!A57 -> 8556 | B18: =IF(_xlfn.XLOOKUP(A18,Test!$A$2:$A$801,Test!$A$2:$A$801,0),"N/A",'News Articles 26'!B57) -> https://resolver.kb.nl/resolve?urn=KBPERS01:003165009:mpeg21:p00001 | C18: ='News Articles 26'!C57 -> Jakarta police intervenes heavily in protests | D18: =IF(B18="N/A","N/A",'News Articles 26'!D57) -> 983e3771990f4604747c53c007b30bab
A19: ='News Articles 26'!A76 -> 8575 | B19: =IF(_xlfn.XLOOKUP(A19,Test!$A$2:$A$801,Test!$A$2:$A$801,0),"N/A",'News Articles 26'!B76) -> https://resolver.kb.nl/resolve?urn=KBPERS01:003161023:mpeg21:p00019 | C19: ='News Articles 26'!C76 -> WTC New York becomes leasing complex | D19: =IF(B19="N/A","N/A",'News Articles 26'!D76) -> 93c3719062504cd79cf9f2bb72d10f62
A20: ='News Articles 26'!A56 -> 8555 | B20: =IF(_xlfn.XLOOKUP(A20,Test!$A$2:$A$801,Test!$A$2:$A$801,0),"N/A",'News Articles 26'!B56) -> https://resolver.kb.nl/resolve?urn=KBPERS01:003159008:mpeg21:p00010 | C20: ='News Articles 26'!C56 -> "VW with Renault in heavy trucks" | D20: =IF(B20="N/A","N/A",'News Articles 26'!D56) -> f940294caba0780fe5eb4c79aedecfe4
A21: ='News Articles 26'!A55 -> 8554 | B21: =IF(_xlfn.XLOOKUP(A21,Test!$A$2:$A$801,Test!$A$2:$A$801,0),"N/A",'News Articles 26'!B55) -> https://resolver.kb.nl/resolve?urn=KBPERS01:003159008:mpeg21:p00009 | C21: ='News Articles 26'!C55 -> Market more balanced after supermarket merger | D21: =IF(B21="N/A","N/A",'News Articles 26'!D55) -> 30ae902e8733877cb177a910fc419f5d
A22: ='News Articles 26'!A61 -> 8560 | B22: =IF(_xlfn.XLOOKUP(A22,Test!$A$2:$A$801,Test!$A$2:$A$801,0),"N/A",'News Articles 26'!B61) -> https://resolver.kb.nl/resolve?urn=KBPERS01:003147011:mpeg21:p00005 | C22: ='News Articles 26'!C61 -> The clog is allowed on the work floor | D22: =IF(B22="N/A","N/A",'News Articles 26'!D61) -> 7fae3bec54118930d59f95cd83c0a7f5
A23: ='News Articles 26'!A60 -> 8559 | B23: =IF(_xlfn.XLOOKUP(A23,Test!$A$2:$A$801,Test!$A$2:$A$801,0),"N/A",'News Articles 26'!B60) -> https://resolver.kb.nl/resolve?urn=KBPERS01:003147006:mpeg21:p00013 | C23: ='News Articles 26'!C60 -> High time for European asylum policy | D23: =IF(B23="N/A","N/A",'News Articles 26'!D60) -> 62acfd6c317bd1fa9def63fa2f8f6f2c
A24: ='News Articles 26'!A54 -> 8553 | B24: =IF(_xlfn.XLOOKUP(A24,Test!$A$2:$A$801,Test!$A$2:$A$801,0),"N/A",'News Articles 26'!B54) -> https://resolver.kb.nl/resolve?urn=KBNRC01:000034634:mpeg21:p002 | C24: ='News Articles 26'!C54 -> IJ tunnel currently under construction over its full length | D24: =IF(B24="N/A","N/A",'News Articles 26'!D54) -> ef7a0e5b1c5ac5a8b27f0ee7920aca67
A25: ='News Articles 26'!A43 -> 8542 | B25: =IF(_xlfn.XLOOKUP(A25,Test!$A$2:$A$801,Test!$A$2:$A$801,0),"N/A",'News Articles 26'!B43) -> https://resolver.kb.nl/resolve?urn=KBNRC01:000031232:mpeg21:p006 | C25: ='News Articles 26'!C43 -> Bad weather hinders rehearsals for an open-air opera performance in Spanga. Mud and water fill the orchestra pit | D25: =IF(B25="N/A","N/A",'News Articles 26'!D43) -> d6efd93254dcaa45e86af90faf20559a
A26: ='News Articles 26'!A51 -> 8550 | B26: =IF(_xlfn.XLOOKUP(A26,Test!$A$2:$A$801,Test!$A$2:$A$801,0),"N/A",'News Articles 26'!B51) -> https://resolver.kb.nl/resolve?urn=KBNRC01:000029055:mpeg21:p003 | C26: ='News Articles 26'!C51 -> Installation of CPN mayor 'historic day' for Beerta | D26: =IF(B26="N/A","N/A",'News Articles 26'!D51) -> d988600c467a985bb10a84023e64ff1e
A27: ='News Articles 26'!A52 -> 8551 | B27: =IF(_xlfn.XLOOKUP(A27,Test!$A$2:$A$801,Test!$A$2:$A$801,0),"N/A",'News Articles 26'!B52) -> https://resolver.kb.nl/resolve?urn=KBNRC01:000029055:mpeg21:p003 | C27: ='News Articles 26'!C52 -> More than 2,000 stutterers are waiting for treatment for their speech impediment | D27: =IF(B27="N/A","N/A",'News Articles 26'!D52) -> 2f3dc1205da8b77a7ebf8e4ee1f8a95d
A28: ='News Articles 26'!A36 -> 8535 | B28: =IF(_xlfn.XLOOKUP(A28,Test!$A$2:$A$801,Test!$A$2:$A$801,0),"N/A",'News Articles 26'!B36) -> https://resolver.kb.nl/resolve?urn=KBNRC01:000028883:mpeg21:p007 | C28: ='News Articles 26'!C36 -> Cabinet cannot deny nor stop the political power of the elderly movement. The illusions of Lubbers' "caring society" | D28: =IF(B28="N/A","N/A",'News Articles 26'!D36) -> c2886321edf3e12a580e48717838d56a
A29: ='News Articles 26'!A35 -> 8534 | B29: =IF(_xlfn.XLOOKUP(A29,Test!$A$2:$A$801,Test!$A$2:$A$801,0),"N/A",'News Articles 26'!B35) -> https://resolver.kb.nl/resolve?urn=KBNRC01:000028883:mpeg21:p003 | C29: ='News Articles 26'!C35 -> Vondelkerk almost as new again | D29: =IF(B29="N/A","N/A",'News Articles 26'!D35) -> 7eaca616ec9bf1033bb8baed4424aea7
A30: ='News Articles 26'!A38 -> 8537 | B30: =IF(_xlfn.XLOOKUP(A30,Test!$A$2:$A$801,Test!$A$2:$A$801,0),"N/A",'News Articles 26'!B38) -> https://resolver.kb.nl/resolve?urn=KBNRC01:000028852:mpeg21:p002 | C30: ='News Articles 26'!C38 -> Coffee house resurrected from ruins | D30: =IF(B30="N/A","N/A",'News Articles 26'!D38) -> 461c0476e694d30691b4830b3817edce
A31: ='News Articles 26'!A37 -> 8536 | B31: =IF(_xlfn.XLOOKUP(A31,Test!$A$2:$A$801,Test!$A$2:$A$801,0),"N/A",'News Articles 26'!B37) -> https://resolver.kb.nl/resolve?urn=KBNRC01:000028840:mpeg21:p001 | C31: ='News Articles 26'!C37 -> Employment plan stumbling block Van Agt Cabinet offers resignation | D31: =IF(B31="N/A","N/A",'News Articles 26'!D37) -> c1f0e5f900eb4927f573c2573bdc7e03
A32: ='News Articles 26'!A41 -> 8540 | B32: =IF(_xlfn.XLOOKUP(A32,Test!$A$2:$A$801,Test!$A$2:$A$801,0),"N/A",'News Articles 26'!B41) -> https://resolver.kb.nl/resolve?urn=KBNRC01:000028505:mpeg21:p005 | C32: ='News Articles 26'!C41 -> Reagan Briefs Congress: Saudis Get Awacs | D32: =IF(B32="N/A","N/A",'News Articles 26'!D41) -> 29ccb1f0e4dd56a95d882ac6a905329f
A33: ='News Articles 26'!A39 -> 8538 | B33: =IF(_xlfn.XLOOKUP(A33,Test!$A$2:$A$801,Test!$A$2:$A$801,0),"N/A",'News Articles 26'!B39) -> https://resolver.kb.nl/resolve?urn=KBNRC01:000027391:mpeg21:p002 | C33: ='News Articles 26'!C39 -> Massive lawsuit threatens Jordaan landlords | D33: =IF(B33="N/A","N/A",'News Articles 26'!D39) -> ef2d773cc5bac4c46b75f7681a8ce001
A34: ='News Articles 26'!A53 -> 8552 | B34: =IF(_xlfn.XLOOKUP(A34,Test!$A$2:$A$801,Test!$A$2:$A$801,0),"N/A",'News Articles 26'!B53) -> https://resolver.kb.nl/resolve?urn=KBNRC01:000026915:mpeg21:p005 | C34: ='News Articles 26'!C53 -> Doubts in the US about the correctness of American Soviet policy | D34: =IF(B34="N/A","N/A",'News Articles 26'!D53) -> 363f49392d332a179c83cc6bea93782f
A35: ='News Articles 26'!A50 -> 8549 | B35: =IF(_xlfn.XLOOKUP(A35,Test!$A$2:$A$801,Test!$A$2:$A$801,0),"N/A",'News Articles 26'!B50) -> https://resolver.kb.nl/resolve?urn=KBNRC01:000026915:mpeg21:p004 | C35: ='News Articles 26'!C50 -> French-German top can talk about their own 'third way' for Western Europe | D35: =IF(B35="N/A","N/A",'News Articles 26'!D50) -> 545c20a559ffc50aaf86efb0c0a94c51
A36: ='News Articles 26'!A49 -> 8548 | B36: =IF(_xlfn.XLOOKUP(A36,Test!$A$2:$A$801,Test!$A$2:$A$801,0),"N/A",'News Articles 26'!B49) -> https://resolver.kb.nl/resolve?urn=KBNRC01:000026915:mpeg21:p003 | C36: ='News Articles 26'!C49 -> French 'objecteurs' ask for political asylum | D36: =IF(B36="N/A","N/A",'News Articles 26'!D49) -> 89e7bb4b80cd32da7acf233f2840b48c
A37: ='News Articles 26'!A32 -> 8531 | B37: =IF(_xlfn.XLOOKUP(A37,Test!$A$2:$A$801,Test!$A$2:$A$801,0),"N/A",'News Articles 26'!B32) -> https://resolver.kb.nl/resolve?urn=ddd:011198836:mpeg21:p003 | C37: ='News Articles 26'!C32 -> Holiday spread in jeopardy for coastal hotels. Tourist flow failed | D37: =IF(B37="N/A","N/A",'News Articles 26'!D32) -> 9853a0842854c38eb1efaf943c2ace04
A38: ='News Articles 26'!A31 -> 8530 | B38: =IF(_xlfn.XLOOKUP(A38,Test!$A$2:$A$801,Test!$A$2:$A$801,0),"N/A",'News Articles 26'!B31) -> https://resolver.kb.nl/resolve?urn=ddd:011198697:mpeg21:p001 | C38: ='News Articles 26'!C31 -> LIBYA HOLDS PROTOTYPE AND CREW Fokker team suspected of espionage | D38: =IF(B38="N/A","N/A",'News Articles 26'!D31) -> ee50742b6e07d29f5ddbdb88c3fa6f33
A39: ='News Articles 26'!A30 -> 8529 | B39: =IF(_xlfn.XLOOKUP(A39,Test!$A$2:$A$801,Test!$A$2:$A$801,0),"N/A",'News Articles 26'!B30) -> https://resolver.kb.nl/resolve?urn=ddd:011198687:mpeg21:p013 | C39: ='News Articles 26'!C30 -> Real Madrid has not seen Cruyff.... | D39: =IF(B39="N/A","N/A",'News Articles 26'!D30) -> 74fc232444af3ea1c1be0dc8c48e8107
A40: ='News Articles 26'!A65 -> 8564 | B40: =IF(_xlfn.XLOOKUP(A40,Test!$A$2:$A$801,Test!$A$2:$A$801,0),"N/A",'News Articles 26'!B65) -> https://resolver.kb.nl/resolve?urn=ddd:011182224:mpeg21:p003 | C40: ='News Articles 26'!C65 -> For The People's Friend. The Jews in Russia. | D40: =IF(B40="N/A","N/A",'News Articles 26'!D65) -> 5434077d0114e9fd78ee8475bb9b02ff
A41: ='News Articles 26'!A64 -> 8563 | B41: =IF(_xlfn.XLOOKUP(A41,Test!$A$2:$A$801,Test!$A$2:$A$801,0),"N/A",'News Articles 26'!B64) -> https://resolver.kb.nl/resolve?urn=ddd:011181418:mpeg21:p001 | C41: ='News Articles 26'!C64 -> Washington's Inauguration. A PROCLAMATION from the President. | D41: =IF(B41="N/A","N/A",'News Articles 26'!D64) -> de27b4068584f1501858105b13c127fb
A42: ='News Articles 26'!A74 -> 8573 | B42: =IF(_xlfn.XLOOKUP(A42,Test!$A$2:$A$801,Test!$A$2:$A$801,0),"N/A",'News Articles 26'!B74) -> https://resolver.kb.nl/resolve?urn=ddd:011017011:mpeg21:p009 | C42: ='News Articles 26'!C74 -> Thirteen years of the Berlin Wall | D42: =IF(B42="N/A","N/A",'News Articles 26'!D74) -> 1f63fe5620a2163beaa0600ee48461f9
A43: ='News Articles 26'!A78 -> 8577 | B43: =IF(_xlfn.XLOOKUP(A43,Test!$A$2:$A$801,Test!$A$2:$A$801,0),"N/A",'News Articles 26'!B78) -> https://resolver.kb.nl/resolve?urn=ddd:010948913:mpeg21:p007 | C43: ='News Articles 26'!C78 -> Empire State burns for a moment | D43: =IF(B43="N/A","N/A",'News Articles 26'!D78) -> bde4f0297f4efc20459e4d920e4e70d3
A44: ='News Articles 26'!A80 -> 8579 | B44: =IF(_xlfn.XLOOKUP(A44,Test!$A$2:$A$801,Test!$A$2:$A$801,0),"N/A",'News Articles 26'!B80) -> https://resolver.kb.nl/resolve?urn=ddd:010645110:mpeg21:p001 | C44: ='News Articles 26'!C80 -> Largest building in the Netherlands from dusty to fresh | D44: =IF(B44="N/A","N/A",'News Articles 26'!D80) -> e07eef7ceac91ec069fa5d45957e2afd
A45: ='News Articles 26'!A46 -> 8545 | B45: =IF(_xlfn.XLOOKUP(A45,Test!$A$2:$A$801,Test!$A$2:$A$801,0),"N/A",'News Articles 26'!B46) -> https://resolver.kb.nl/resolve?urn=ddd:010644780:mpeg21:p016 | C45: ='News Articles 26'!C46 -> First Lady Clinton changes White House | D45: =IF(B45="N/A","N/A",'News Articles 26'!D46) -> 6d38796eca75d898d4a3da8adc664deb
A46: ='News Articles 26'!A45 -> 8544 | B46: =IF(_xlfn.XLOOKUP(A46,Test!$A$2:$A$801,Test!$A$2:$A$801,0),"N/A",'News Articles 26'!B45) -> https://resolver.kb.nl/resolve?urn=ddd:010644780:mpeg21:p009 | C46: ='News Articles 26'!C45 -> Le Pen is running for president | D46: =IF(B46="N/A","N/A",'News Articles 26'!D45) -> d59b02ac506f71d26d74afba4c71820e
A47: ='News Articles 26'!A77 -> 8576 | B47: =IF(_xlfn.XLOOKUP(A47,Test!$A$2:$A$801,Test!$A$2:$A$801,0),"N/A",'News Articles 26'!B77) -> https://resolver.kb.nl/resolve?urn=ddd:010637884:mpeg21:p003 | C47: ='News Articles 26'!C77 -> Explosion in New York | D47: =IF(B47="N/A","N/A",'News Articles 26'!D77) -> 8374ad7230bd147a1eced64df7c643cf
A48: ='News Articles 26'!A75 -> 8574 | B48: =IF(_xlfn.XLOOKUP(A48,Test!$A$2:$A$801,Test!$A$2:$A$801,0),"N/A",'News Articles 26'!B75) -> https://resolver.kb.nl/resolve?urn=ddd:010623845:mpeg21:p009 | C48: ='News Articles 26'!C75 -> Employment offices may grant work permits. Ample job opportunities for East Germans | D48: =IF(B48="N/A","N/A",'News Articles 26'!D75) -> f7487466e0219f2d218bea3cd626185b
A49: ='News Articles 26'!A16 -> 8515 | B49: =IF(_xlfn.XLOOKUP(A49,Test!$A$2:$A$801,Test!$A$2:$A$801,0),"N/A",'News Articles 26'!B16) -> https://resolver.kb.nl/resolve?urn=ABCDDD:010882366:mpeg21:p001 | C49: ='News Articles 26'!C16 -> AT LAST APOLLO LAUNCH Researchers want additional moon flights | D49: =IF(B49="N/A","N/A",'News Articles 26'!D16) -> 7305276d7d262b9deca863ae7d26a9b4
A50: ='News Articles 26'!A48 -> 8547 | B50: =IF(_xlfn.XLOOKUP(A50,Test!$A$2:$A$801,Test!$A$2:$A$801,0),"N/A",'News Articles 26'!B48) -> https://resolver.kb.nl/resolve?urn=ABCDDD:010882031:mpeg21:p007 | C50: ='News Articles 26'!C48 -> OPPONENTS NUCLEAR ENERGY Germans ask for asylum | D50: =IF(B50="N/A","N/A",'News Articles 26'!D48) -> de5c435054630ba3d4636c95994ef4c2
A51: ='News Articles 26'!A24 -> 8523 | B51: =IF(_xlfn.XLOOKUP(A51,Test!$A$2:$A$801,Test!$A$2:$A$801,0),"N/A",'News Articles 26'!B24) -> https://resolver.kb.nl/resolve?urn=ABCDDD:010880416:mpeg21:p010 | C51: ='News Articles 26'!C24 -> Chat between HHIIC and Kampong DOUBLE HOCKEY ROUND EXCLUDES SURPRISE | D51: =IF(B51="N/A","N/A",'News Articles 26'!D24) -> 72b10db254d21789e27c573abf5e5059
A52: ='News Articles 26'!A25 -> 8524 | B52: =IF(_xlfn.XLOOKUP(A52,Test!$A$2:$A$801,Test!$A$2:$A$801,0),"N/A",'News Articles 26'!B25) -> https://resolver.kb.nl/resolve?urn=ABCDDD:010880416:mpeg21:p010 | C52: ='News Articles 26'!C25 -> Isaksson higher again: 5.54 m. | D52: =IF(B52="N/A","N/A",'News Articles 26'!D25) -> 333595c317747bf8e07c50cb1fd56ba3
A53: ='News Articles 26'!A22 -> 8521 | B53: =IF(_xlfn.XLOOKUP(A53,Test!$A$2:$A$801,Test!$A$2:$A$801,0),"N/A",'News Articles 26'!B22) -> https://resolver.kb.nl/resolve?urn=ABCDDD:010880416:mpeg21:p008 | C53: ='News Articles 26'!C22 -> Heerenveen loses points in mediocre Frisian derby | D53: =IF(B53="N/A","N/A",'News Articles 26'!D22) -> a5ed38b681f1772d1f6d53b10a679350
A54: ='News Articles 26'!A23 -> 8522 | B54: =IF(_xlfn.XLOOKUP(A54,Test!$A$2:$A$801,Test!$A$2:$A$801,0),"N/A",'News Articles 26'!B23) -> https://resolver.kb.nl/resolve?urn=ABCDDD:010880416:mpeg21:p008 | C54: ='News Articles 26'!C23 -> Brugge two points ahead of ANDERLECHT FALLS OVER LIERSE SK Tough duels at Arsenal - Stoke | D54: =IF(B54="N/A","N/A",'News Articles 26'!D23) -> 19c16f14d7c6a4bfc7b7905aaa078291
A55: ='News Articles 26'!A21 -> 8520 | B55: =IF(_xlfn.XLOOKUP(A55,Test!$A$2:$A$801,Test!$A$2:$A$801,0),"N/A",'News Articles 26'!B21) -> https://resolver.kb.nl/resolve?urn=ABCDDD:010880416:mpeg21:p005 | C55: ='News Articles 26'!C21 -> ACOUSTIC PLAYGROUND IN CITY MUSEUM | D55: =IF(B55="N/A","N/A",'News Articles 26'!D21) -> c5fd0d44f13a29e8bf52784c9bed581f
A56: ='News Articles 26'!A19 -> 8518 | B56: =IF(_xlfn.XLOOKUP(A56,Test!$A$2:$A$801,Test!$A$2:$A$801,0),"N/A",'News Articles 26'!B19) -> https://resolver.kb.nl/resolve?urn=ABCDDD:010880409:mpeg21:p002 | C56: ='News Articles 26'!C19 -> Dividend for 1971 is reduced Akzo writes down 150 million on surplus factories | D56: =IF(B56="N/A","N/A",'News Articles 26'!D19) -> 51ea0aad08832b2d93c4c01c68f14a14
A57: ='News Articles 26'!A15 -> 8514 | B57: =IF(_xlfn.XLOOKUP(A57,Test!$A$2:$A$801,Test!$A$2:$A$801,0),"N/A",'News Articles 26'!B15) -> https://resolver.kb.nl/resolve?urn=ABCDDD:010880263:mpeg21:p015 | C57: ='News Articles 26'!C15 -> WITH LEAD IN THE LEGS TO SALLANCHES Jan Janssen saves from difficult mountain stage | D57: =IF(B57="N/A","N/A",'News Articles 26'!D15) -> 5d6d158237dc4e813f6bdddb3e655952
A58: ='News Articles 26'!A14 -> 8513 | B58: =IF(_xlfn.XLOOKUP(A58,Test!$A$2:$A$801,Test!$A$2:$A$801,0),"N/A",'News Articles 26'!B14) -> https://resolver.kb.nl/resolve?urn=ABCDDD:010880263:mpeg21:p011 | C58: ='News Articles 26'!C14 -> TOURISM TO POLAND IS ROWING SLOWLY | D58: =IF(B58="N/A","N/A",'News Articles 26'!D14) -> 40c33ee9c01a7fb368b31a5981847927
A59: ='News Articles 26'!A13 -> 8512 | B59: =IF(_xlfn.XLOOKUP(A59,Test!$A$2:$A$801,Test!$A$2:$A$801,0),"N/A",'News Articles 26'!B13) -> https://resolver.kb.nl/resolve?urn=ABCDDD:010880263:mpeg21:p001 | C59: ='News Articles 26'!C13 -> LETTER FROM WARSAW REJECTED Doebsek: we will continue | D59: =IF(B59="N/A","N/A",'News Articles 26'!D13) -> b7bc7d667610be21b9799fe39ee86995
A60: ='News Articles 26'!A100 -> 8599 | B60: =IF(_xlfn.XLOOKUP(A60,Test!$A$2:$A$801,Test!$A$2:$A$801,0),"N/A",'News Articles 26'!B100) -> https://resolver.kb.nl/resolve?urn=ABCDDD:010866779:mpeg21:p009 | C60: ='News Articles 26'!C100 -> Is a pharmacist a retailer or healthcare provider? | D60: =IF(B60="N/A","N/A",'News Articles 26'!D100) -> ec953dd7fb3eb2980b02dce8d4b1e03e
A61: ='News Articles 26'!A98 -> 8597 | B61: =IF(_xlfn.XLOOKUP(A61,Test!$A$2:$A$801,Test!$A$2:$A$801,0),"N/A",'News Articles 26'!B98) -> https://resolver.kb.nl/resolve?urn=ABCDDD:010866779:mpeg21:p005 | C61: ='News Articles 26'!C98 -> Israeli army begins retreat from Gaza Strip | D61: =IF(B61="N/A","N/A",'News Articles 26'!D98) -> 835367d0750b20ace36608576a0d8cad
A62: ='News Articles 26'!A97 -> 8596 | B62: =IF(_xlfn.XLOOKUP(A62,Test!$A$2:$A$801,Test!$A$2:$A$801,0),"N/A",'News Articles 26'!B97) -> https://resolver.kb.nl/resolve?urn=ABCDDD:010866779:mpeg21:p004 | C62: ='News Articles 26'!C97 -> Only the national parliaments decide the future of Europe. The European Parliament remains a weak link | D62: =IF(B62="N/A","N/A",'News Articles 26'!D97) -> a91817388cf7a4a24ad3bb5597ec1ff5
A63: ='News Articles 26'!A94 -> 8593 | B63: =IF(_xlfn.XLOOKUP(A63,Test!$A$2:$A$801,Test!$A$2:$A$801,0),"N/A",'News Articles 26'!B94) -> https://resolver.kb.nl/resolve?urn=ABCDDD:010866774:mpeg21:p006 | C63: ='News Articles 26'!C94 -> Rutskoy makes a comeback on the political stage | D63: =IF(B63="N/A","N/A",'News Articles 26'!D94) -> c11aa3ad1840f9b2141a60998a3a848f
A64: ='News Articles 26'!A96 -> 8595 | B64: =IF(_xlfn.XLOOKUP(A64,Test!$A$2:$A$801,Test!$A$2:$A$801,0),"N/A",'News Articles 26'!B96) -> https://resolver.kb.nl/resolve?urn=ABCDDD:010866774:mpeg21:p005 | C64: ='News Articles 26'!C96 -> A kindred spirit of Noriega becomes president of Panama | D64: =IF(B64="N/A","N/A",'News Articles 26'!D96) -> d555142d747f0b32b1367e1055938d00
A65: ='News Articles 26'!A95 -> 8594 | B65: =IF(_xlfn.XLOOKUP(A65,Test!$A$2:$A$801,Test!$A$2:$A$801,0),"N/A",'News Articles 26'!B95) -> https://resolver.kb.nl/resolve?urn=ABCDDD:010866774:mpeg21:p002 | C65: ='News Articles 26'!C95 -> Director of electricity producer SEP advocates the introduction of 'cleaned' competition. Recession puts pressure on increase in energy consumption | D65: =IF(B65="N/A","N/A",'News Articles 26'!D95) -> 6924fa40bd2b9390819b3382bf008b50
A66: ='News Articles 26'!A93 -> 8592 | B66: =IF(_xlfn.XLOOKUP(A66,Test!$A$2:$A$801,Test!$A$2:$A$801,0),"N/A",'News Articles 26'!B93) -> https://resolver.kb.nl/resolve?urn=ABCDDD:010866774:mpeg21:p001 | C66: ='News Articles 26'!C93 -> South Africa's first black president promises crowds in Cape Town jobs and reconciliation Emotional scenes during Mandela's election | D66: =IF(B66="N/A","N/A",'News Articles 26'!D93) -> d536a1e238dc27fbeae42bccb560c924
A67: ='News Articles 26'!A92 -> 8591 | B67: =IF(_xlfn.XLOOKUP(A67,Test!$A$2:$A$801,Test!$A$2:$A$801,0),"N/A",'News Articles 26'!B92) -> https://resolver.kb.nl/resolve?urn=ABCDDD:010866768:mpeg21:p013 | C67: ='News Articles 26'!C92 -> A good debate on TV scores points | D67: =IF(B67="N/A","N/A",'News Articles 26'!D92) -> 12ed56f21f33393cff06797ae4d4f30f
A68: ='News Articles 26'!A90 -> 8589 | B68: =IF(_xlfn.XLOOKUP(A68,Test!$A$2:$A$801,Test!$A$2:$A$801,0),"N/A",'News Articles 26'!B90) -> https://resolver.kb.nl/resolve?urn=ABCDDD:010866768:mpeg21:p006 | C68: ='News Articles 26'!C90 -> Tremelo mourns the Pope who does not come | D68: =IF(B68="N/A","N/A",'News Articles 26'!D90) -> 123afb66ccf848025419c43d52a7d85b
A69: ='News Articles 26'!A88 -> 8587 | B69: =IF(_xlfn.XLOOKUP(A69,Test!$A$2:$A$801,Test!$A$2:$A$801,0),"N/A",'News Articles 26'!B88) -> https://resolver.kb.nl/resolve?urn=ABCDDD:010866768:mpeg21:p002 | C69: ='News Articles 26'!C88 -> African imports put pressure on floriculture | D69: =IF(B69="N/A","N/A",'News Articles 26'!D88) -> eed86dd1509cabcd0ea05ab735a9dc23
A70: ='News Articles 26'!A101 -> 8600 | B70: =IF(_xlfn.XLOOKUP(A70,Test!$A$2:$A$801,Test!$A$2:$A$801,0),"N/A",'News Articles 26'!B101) -> https://resolver.kb.nl/resolve?urn=ABCDDD:010866563:mpeg21:p009 | C70: ='News Articles 26'!C101 -> More Europe does not automatically mean more power for Brussels | D70: =IF(B70="N/A","N/A",'News Articles 26'!D101) -> 2aef436d8589b24d303c598ad5736f00
A71: ='News Articles 26'!A33 -> 8532 | B71: =IF(_xlfn.XLOOKUP(A71,Test!$A$2:$A$801,Test!$A$2:$A$801,0),"N/A",'News Articles 26'!B33) -> https://resolver.kb.nl/resolve?urn=ABCDDD:010823895:mpeg21:p001 | C71: ='News Articles 26'!C33 -> Mr Willem Aantjes rejects political positions CDA stunned and defeated | D71: =IF(B71="N/A","N/A",'News Articles 26'!D33) -> c4507ad021865cc5d0f89fc2ce3edc5a
A72: ='News Articles 26'!A72 -> 8571 | B72: =IF(_xlfn.XLOOKUP(A72,Test!$A$2:$A$801,Test!$A$2:$A$801,0),"N/A",'News Articles 26'!B72) -> https://resolver.kb.nl/resolve?urn=ABCDDD:010819797:mpeg21:p001 | C72: ='News Articles 26'!C72 -> Court bans US actions against Nicaragua | D72: =IF(B72="N/A","N/A",'News Articles 26'!D72) -> 3094c8d2d24724cd7bc99f0250479f1a
A73: ='News Articles 26'!A71 -> 8570 | B73: =IF(_xlfn.XLOOKUP(A73,Test!$A$2:$A$801,Test!$A$2:$A$801,0),"N/A",'News Articles 26'!B71) -> https://resolver.kb.nl/resolve?urn=ABCDDD:010819663:mpeg21:p009 | C73: ='News Articles 26'!C71 -> SPORT Impending departure of star players Cruijff and Gullit Feyenoord: title now, but worries later | D73: =IF(B73="N/A","N/A",'News Articles 26'!D71) -> 83d92d612e4869d16c1c2b7d8411fee9
A74: ='News Articles 26'!A70 -> 8569 | B74: =IF(_xlfn.XLOOKUP(A74,Test!$A$2:$A$801,Test!$A$2:$A$801,0),"N/A",'News Articles 26'!B70) -> https://resolver.kb.nl/resolve?urn=ABCDDD:010819663:mpeg21:p006 | C74: ='News Articles 26'!C70 -> Tilburg continues to provide help, but in a different way. Polish hospitals also need knowledge | D74: =IF(B74="N/A","N/A",'News Articles 26'!D70) -> 6d0883565decb2eee7a76022ad60ce15
A75: ='News Articles 26'!A69 -> 8568 | B75: =IF(_xlfn.XLOOKUP(A75,Test!$A$2:$A$801,Test!$A$2:$A$801,0),"N/A",'News Articles 26'!B69) -> https://resolver.kb.nl/resolve?urn=ABCDDD:010819663:mpeg21:p001 | C75: ='News Articles 26'!C69 -> Soviet Union does not avoid discussions with Americans | D75: =IF(B75="N/A","N/A",'News Articles 26'!D69) -> 0c2ae1ed36cd06fac16378ada8ced9ac
A76: ='News Articles 26'!A68 -> 8567 | B76: =IF(_xlfn.XLOOKUP(A76,Test!$A$2:$A$801,Test!$A$2:$A$801,0),"N/A",'News Articles 26'!B68) -> https://resolver.kb.nl/resolve?urn=ABCDDD:010819645:mpeg21:p007 | C76: ='News Articles 26'!C68 -> Space shuttle takes off on a repair flight | D76: =IF(B76="N/A","N/A",'News Articles 26'!D68) -> 2fe101b78fb91802455d4c8f5243c2be
A77: ='News Articles 26'!A66 -> 8565 | B77: =IF(_xlfn.XLOOKUP(A77,Test!$A$2:$A$801,Test!$A$2:$A$801,0),"N/A",'News Articles 26'!B66) -> https://resolver.kb.nl/resolve?urn=ABCDDD:010819645:mpeg21:p004 | C77: ='News Articles 26'!C66 -> Utrecht continues to grumble about the loss of its own orchestra | D77: =IF(B77="N/A","N/A",'News Articles 26'!D66) -> d41478f6cf679f21fc7c458d97da628f
A78: ='News Articles 26'!A67 -> 8566 | B78: =IF(_xlfn.XLOOKUP(A78,Test!$A$2:$A$801,Test!$A$2:$A$801,0),"N/A",'News Articles 26'!B67) -> https://resolver.kb.nl/resolve?urn=ABCDDD:010819645:mpeg21:p004 | C78: ='News Articles 26'!C67 -> From 'rebel club to famous company' by Eva van Schaik | D78: =IF(B78="N/A","N/A",'News Articles 26'!D67) -> face51f3e0d76c40e8b784cd8ae402d4
A79: ='News Articles 26'!A11 -> 8510 | B79: =IF(_xlfn.XLOOKUP(A79,Test!$A$2:$A$801,Test!$A$2:$A$801,0),"N/A",'News Articles 26'!B11) -> https://resolver.kb.nl/resolve?urn=ABCDDD:010814047:mpeg21:p001 | C79: ='News Articles 26'!C11 -> SAIGON STRENGTHENS ARMY 'to prepare peace' | D79: =IF(B79="N/A","N/A",'News Articles 26'!D11) -> c032a4cdc9beb794e1716b5e8303136d
A80: ='News Articles 26'!A9 -> 8508 | B80: =IF(_xlfn.XLOOKUP(A80,Test!$A$2:$A$801,Test!$A$2:$A$801,0),"N/A",'News Articles 26'!B9) -> https://resolver.kb.nl/resolve?urn=ABCDDD:010814016:mpeg21:p001 | C80: ='News Articles 26'!C9 -> Heavy fighting during Israeli punitive expedition in Jordan TWELVE HOURS OF WAR IN MIDDLE EAST TEL AVIV/AMMAN | D80: =IF(B80="N/A","N/A",'News Articles 26'!D9) -> 084d9c4182d5568b0d8903e874894cf0
A81: ='News Articles 26'!A11517 -> 20016 | B81: =IF(_xlfn.XLOOKUP(A81,Test!$A$2:$A$801,Test!$A$2:$A$801,0),"N/A",'News Articles 26'!B11517) -> https://assets.msn.com/labs/mind/BBy5rVe.html | C81: ='News Articles 26'!C11517 -> Best Sports Car Deals for October | D81: =IF(B81="N/A","N/A",'News Articles 26'!D11517) -> 56e4cfc97ab445d88b960609a00401d9
A82: ='News Articles 26'!A2190 -> 10689 | B82: =IF(_xlfn.XLOOKUP(A82,Test!$A$2:$A$801,Test!$A$2:$A$801,0),"N/A",'News Articles 26'!B2190) -> https://assets.msn.com/labs/mind/BBWzxoR.html | C82: ='News Articles 26'!C2190 -> Robert Kraft reportedly wants Rob Gronkowski back for the playoffs | D82: =IF(B82="N/A","N/A",'News Articles 26'!D2190) -> 6e86eb6bed1c4e5ca3b302902a9015a8
A83: ='News Articles 26'!A2185 -> 10684 | B83: =IF(_xlfn.XLOOKUP(A83,Test!$A$2:$A$801,Test!$A$2:$A$801,0),"N/A",'News Articles 26'!B2185) -> https://assets.msn.com/labs/mind/BBWzx8x.html | C83: ='News Articles 26'!C2185 -> Making a Case for A.J. Hinch as Manager of the Year | D83: =IF(B83="N/A","N/A",'News Articles 26'!D2185) -> c022c2af04cb46a181aab23c8960ec1b
A84: ='News Articles 26'!A2180 -> 10679 | B84: =IF(_xlfn.XLOOKUP(A84,Test!$A$2:$A$801,Test!$A$2:$A$801,0),"N/A",'News Articles 26'!B2180) -> https://assets.msn.com/labs/mind/BBWzwvv.html | C84: ='News Articles 26'!C2180 -> Stockton boxer Gabe Flores, Jr. improves to 16-0 with win in Fresno | D84: =IF(B84="N/A","N/A",'News Articles 26'!D2180) -> df15f4f5408a4a00ba972e502d612d23
A85: ='News Articles 26'!A2165 -> 10664 | B85: =IF(_xlfn.XLOOKUP(A85,Test!$A$2:$A$801,Test!$A$2:$A$801,0),"N/A",'News Articles 26'!B2165) -> https://assets.msn.com/labs/mind/BBWzwIB.html | C85: ='News Articles 26'!C2165 -> Microsoft CEO Satya Nadella says this piece of advice impacted him profoundly | D85: =IF(B85="N/A","N/A",'News Articles 26'!D2165) -> 6b8c20ac45904bd0876ac87660d865f1
A86: ='News Articles 26'!A2161 -> 10660 | B86: =IF(_xlfn.XLOOKUP(A86,Test!$A$2:$A$801,Test!$A$2:$A$801,0),"N/A",'News Articles 26'!B2161) -> https://assets.msn.com/labs/mind/BBWzwFt.html | C86: ='News Articles 26'!C2161 -> NFL overreactions: Vikings assert themselves as NFC contenders | D86: =IF(B86="N/A","N/A",'News Articles 26'!D2161) -> 8ac8c39d63c646679d5ffdfa33586e07
A87: ='News Articles 26'!A2168 -> 10667 | B87: =IF(_xlfn.XLOOKUP(A87,Test!$A$2:$A$801,Test!$A$2:$A$801,0),"N/A",'News Articles 26'!B2168) -> https://assets.msn.com/labs/mind/BBWzwbi.html | C87: ='News Articles 26'!C2168 -> Best, worst QB performances from NFL Week 10 | D87: =IF(B87="N/A","N/A",'News Articles 26'!D2168) -> 3fe2d5b76ff943b1a88e5d4551b815f6
A88: ='News Articles 26'!A2157 -> 10656 | B88: =IF(_xlfn.XLOOKUP(A88,Test!$A$2:$A$801,Test!$A$2:$A$801,0),"N/A",'News Articles 26'!B2157) -> https://assets.msn.com/labs/mind/BBWzw7T.html | C88: ='News Articles 26'!C2157 -> Linval Joseph had knee surgery this week | D88: =IF(B88="N/A","N/A",'News Articles 26'!D2157) -> 6b97460d53fe4302991aa54895a93492
A89: ='News Articles 26'!A2150 -> 10649 | B89: =IF(_xlfn.XLOOKUP(A89,Test!$A$2:$A$801,Test!$A$2:$A$801,0),"N/A",'News Articles 26'!B2150) -> https://assets.msn.com/labs/mind/BBWzvKx.html | C89: ='News Articles 26'!C2150 -> Helicopter Drops Load on Crowdy Bay Bushfire in New South Wales | D89: =IF(B89="N/A","N/A",'News Articles 26'!D2150) -> 768f77ed849b4dfbbd2d8e0b54f0df80
A90: ='News Articles 26'!A2145 -> 10644 | B90: =IF(_xlfn.XLOOKUP(A90,Test!$A$2:$A$801,Test!$A$2:$A$801,0),"N/A",'News Articles 26'!B2145) -> https://assets.msn.com/labs/mind/BBWzvGP.html | C90: ='News Articles 26'!C2145 -> Top takeaways from Sunday's Week 10 NFL action | D90: =IF(B90="N/A","N/A",'News Articles 26'!D2145) -> b23571ac182f42bba00c9a6c51d2cc4b
A91: ='News Articles 26'!A2143 -> 10642 | B91: =IF(_xlfn.XLOOKUP(A91,Test!$A$2:$A$801,Test!$A$2:$A$801,0),"N/A",'News Articles 26'!B2143) -> https://assets.msn.com/labs/mind/BBWzvFE.html | C91: ='News Articles 26'!C2143 -> Man Fatally Shot By Off-Duty Richmond Police Officer In Vallejo | D91: =IF(B91="N/A","N/A",'News Articles 26'!D2143) -> b023f02eeac34a4cabd9a856a80ca8b0
A92: ='News Articles 26'!A1989 -> 10488 | B92: =IF(_xlfn.XLOOKUP(A92,Test!$A$2:$A$801,Test!$A$2:$A$801,0),"N/A",'News Articles 26'!B1989) -> https://assets.msn.com/labs/mind/BBWzV2t.html | C92: ='News Articles 26'!C1989 -> Here's what to expect from Monday's weather forecast | D92: =IF(B92="N/A","N/A",'News Articles 26'!D1989) -> 1f6b02db23f046809c7e307902c5ec83
A93: ='News Articles 26'!A11770 -> 20269 | B93: =IF(_xlfn.XLOOKUP(A93,Test!$A$2:$A$801,Test!$A$2:$A$801,0),"N/A",'News Articles 26'!B11770) -> https://assets.msn.com/labs/mind/BBWzTtA.html | C93: ='News Articles 26'!C11770 -> Huber Heights YMCA to be first 24-hour center in Dayton-area | D93: =IF(B93="N/A","N/A",'News Articles 26'!D11770) -> b40ef90d958c4d77b7c0c8902ba2d69a
A94: ='News Articles 26'!A1967 -> 10466 | B94: =IF(_xlfn.XLOOKUP(A94,Test!$A$2:$A$801,Test!$A$2:$A$801,0),"N/A",'News Articles 26'!B1967) -> https://assets.msn.com/labs/mind/BBWzTqG.html | C94: ='News Articles 26'!C1967 -> Detroit Lions' Darius Slay: Things will get 'ugly' if we don't win out | D94: =IF(B94="N/A","N/A",'News Articles 26'!D1967) -> 02691918a1df465f87bcf003d573b56e
A95: ='News Articles 26'!A1953 -> 10452 | B95: =IF(_xlfn.XLOOKUP(A95,Test!$A$2:$A$801,Test!$A$2:$A$801,0),"N/A",'News Articles 26'!B1953) -> https://assets.msn.com/labs/mind/BBWzTFi.html | C95: ='News Articles 26'!C1953 -> Off-duty Richmond officer shoots, kills man, Vallejo police say | D95: =IF(B95="N/A","N/A",'News Articles 26'!D1953) -> fea6e0e3980b49aa9e6238d595a0ee08
A96: ='News Articles 26'!A1917 -> 10416 | B96: =IF(_xlfn.XLOOKUP(A96,Test!$A$2:$A$801,Test!$A$2:$A$801,0),"N/A",'News Articles 26'!B1917) -> https://assets.msn.com/labs/mind/BBWzRT4.html | C96: ='News Articles 26'!C1917 -> Nautilus surfaces with new look, safety features | D96: =IF(B96="N/A","N/A",'News Articles 26'!D1917) -> 0cb1cd75c0724f609a59db5d3f21a9e1
A97: ='News Articles 26'!A1926 -> 10425 | B97: =IF(_xlfn.XLOOKUP(A97,Test!$A$2:$A$801,Test!$A$2:$A$801,0),"N/A",'News Articles 26'!B1926) -> https://assets.msn.com/labs/mind/BBWzRnD.html | C97: ='News Articles 26'!C1926 -> Historic Plant City Coronet Bungalow Up For Sale | D97: =IF(B97="N/A","N/A",'News Articles 26'!D1926) -> 502357a70e3f4f6a9f7bf88f05102611
A98: ='News Articles 26'!A11516 -> 20015 | B98: =IF(_xlfn.XLOOKUP(A98,Test!$A$2:$A$801,Test!$A$2:$A$801,0),"N/A",'News Articles 26'!B11516) -> https://assets.msn.com/labs/mind/BBWzQuK.html | C98: ='News Articles 26'!C11516 -> How the Sounders won MLS Cup | D98: =IF(B98="N/A","N/A",'News Articles 26'!D11516) -> f8e490988e834089ac425fe7090b4050
A99: ='News Articles 26'!A11515 -> 20014 | B99: =IF(_xlfn.XLOOKUP(A99,Test!$A$2:$A$801,Test!$A$2:$A$801,0),"N/A",'News Articles 26'!B11515) -> https://assets.msn.com/labs/mind/BBWzQJK.html | C99: ='News Articles 26'!C11515 -> Adapting, Learning And Soul Searching: Reflecting On Woolsey Fire | D99: =IF(B99="N/A","N/A",'News Articles 26'!D11515) -> 3b00dd7b89ce45078edb8fac63cb77f6
A100: ='News Articles 26'!A15181 -> 23680 | B100: =IF(_xlfn.XLOOKUP(A100,Test!$A$2:$A$801,Test!$A$2:$A$801,0),"N/A",'News Articles 26'!B15181) -> https://assets.msn.com/labs/mind/BBWzQEU.html | C100: ='News Articles 26'!C15181 -> CNN reporter: This is the tense calm after protester shot | D100: =IF(B100="N/A","N/A",'News Articles 26'!D15181) -> cff84d1b64094d84867ee5bcb64a7a87
...

Sheet Survey
A1: article_id | B1: article_url | C1: article_title | D1: image_id
A2: 8511 | B2: https://resolver.kb.nl/resolve?urn=ABCDDD:010880247:mpeg21:p001 | C2: Landslide French elections De Gaulle's great triumph: absolute majority | D2: dd01a756e57d52f9a86b53fed235c7fb
A3: 8516 | B3: https://resolver.kb.nl/resolve?urn=ABCDDD:010882366:mpeg21:p001 | C3: British-Dutch cooperation MARINE DEPLOYED ON OIL ROUTE Frigate patrol to Indian Ocean | D3: bdf3112dfa9b3371b12c51649225dc44
A4: 8519 | B4: https://resolver.kb.nl/resolve?urn=ABCDDD:010880416:mpeg21:p003 | C4: MORE THAN MILLION SPECTATORS Departure of Apollo 16 went smoothly | D4: b8e61a11c988641a045c570eb33a88e3
A5: 8526 | B5: https://resolver.kb.nl/resolve?urn=ABCDDD:010880796:mpeg21:p001 | C5: Fifty thousand demonstrators in Lisbon | D5: 416e267d2780fffd044541afb21d42ae
A6: 8546 | B6: https://resolver.kb.nl/resolve?urn=ddd:011235935:mpeg21:p007 | C6: NO ATTACK ON BALKANS Brezhnev calms Tito's fears | D6: 4ee97bdf7dd3175c3507b7a6dce3a7bd
A7: 8598 | B7: https://resolver.kb.nl/resolve?urn=ABCDDD:010866779:mpeg21:p006 | C7: At least 60,000 Hutu's flee Rwandan capital Tutsi rebels surround Kigali | D7: f5c7d906aa8ef471c19232a73c2fe88e
A8: 8865 | B8: https://assets.msn.com/labs/mind/AADcUqA.html | C8: Release of whales from notorious Russia 'whale jail' complete | D8: 38123da22ae44e30ab899e425a320d00
A9: 9181 | B9: https://assets.msn.com/labs/mind/AAJX5z6.html | C9: Mercury transit is coming to a sky near you Monday. And it won't happen again until 2032. | D9: 5873e024b2114c63a7242336b8618011
A10: 9621 | B10: https://assets.msn.com/labs/mind/AAJTJOp.html | C10: Cincinnati Zoo pairs up cute rescue dog Remus and baby cheetah Kris for a 'BFF sleepover' | D10: 13e7bf82e6b7458ca72e15f0796befd1
A11: 10741 | B11: https://assets.msn.com/labs/mind/BBWE2bj.html | C11: Sydney Landmarks Shrouded in Haze From New South Wales Fires | D11: f1aa185e3b254b818cf856b7f595f77d
A12: 11115 | B12: https://assets.msn.com/labs/mind/BBWE7xl.html | C12: Meteor spotted streaking across the midwest sky | D12: 2183b9267b9c480a9d1327f17c38bd78
A13: 11292 | B13: https://assets.msn.com/labs/mind/BBWEA7Y.html | C13: NASA Spots Massive, Trippy Thermonuclear Blast | D13: 7b17f91c5d50430ebb095c1542d6d468
... A36: 23503 | B36: https://assets.msn.com/labs/mind/BBWybSc.html | C36: American forces on patrol amid contentious Syrian offensive | D36: 468e263e5ab5453f99c3c1b95b732766
